{
    "valid": {
        "title": "Test Post Title",
        "body": "This is a test post body with meaningful content that can be used for API testing purposes.",
        "userId": 1
    },
    "long_content": {
        "title": "This is a very long title that tests the limits of the title field and ensures proper validation is in place for content length restrictions",
        "body": "This is an extremely long post body that is designed to test the maximum length limits of the body field. It contains multiple sentences and paragraphs to simulate real-world content. Lorem ipsum dolor sit amet, consectetur adipiscing elit. Sed do eiusmod tempor incididunt ut labore et dolore magna aliqua. Ut enim ad minim veniam, quis nostrud exercitation ullamco laboris nisi ut aliquip ex ea commodo consequat. Duis aute irure dolor in reprehenderit in voluptate velit esse cillum dolore eu fugiat nulla pariatur. Excepteur sint occaecat cupidatat non proident, sunt in culpa qui officia deserunt mollit anim id est laborum.",
        "userId": 1
    },
    "empty_fields": {
        "title": "",
        "body": "",
        "userId": 0
    },
    "special_characters": {
        "title": "Special Characters: !@#$%^&*()_+-=[]{}|;':\",./<>?",
        "body": "Testing special characters in body: àáâãäåæçèéêëìíîïðñòóôõöøùúûüýþÿ",
        "userId": 1
    },
    "html_content": {
        "title": "HTML Content Test",
        "body": "<p>This is a <strong>test</strong> with <em>HTML</em> content including <a href='#'>links</a> and <script>alert('xss')</script>",
        "userId": 1
    },
    "unicode_content": {
        "title": "Unicode Test: 🚀 Testing Emojis and Unicode Characters",
        "body": "Testing various unicode characters: 中文 العربية русский язык 日本語 한국어 हिन्दी",
        "userId": 1
    },
    "bulk_posts": [
        {
            "title": "First Test Post",
            "body": "This is the first test post for bulk operations.",
            "userId": 1
        },
        {
            "title": "Second Test Post",
            "body": "This is the second test post for bulk operations.",
            "userId": 2
        },
        {
            "title": "Third Test Post",
            "body": "This is the third test post for bulk operations.",
            "userId": 3
        },
        {
            "title": "Fourth Test Post",
            "body": "This is the fourth test post for bulk operations.",
            "userId": 1
        },
        {
            "title": "Fifth Test Post",
            "body": "This is the fifth test post for bulk operations.",
            "userId": 2
        }
    ]
} 